{
    "first": [
        {
            "value": "鼠疫",
            "label": "鼠疫"
        },
        {
            "value": "霍乱",
            "label": "霍乱"
        }
    ],
    "second": [
        {
            "value": "传染性非典型肺炎",
            "label": "传染性非典型肺炎"
        },
        {
            "value": "艾滋病病人",
            "label": "艾滋病病人"
        },
        {
            "value": "HIV",
            "label": "HIV"
        },
        {
            "value": "甲型病毒性肝炎",
            "label": "甲型病毒性肝炎"
        },
        {
            "value": "乙型病毒性肝炎",
            "label": "乙型病毒性肝炎"
        },
        {
            "value": "丙型病毒性肝炎",
            "label": "丙型病毒性肝炎"
        },
        {
            "value": "戊型病毒性肝炎",
            "label": "戊型病毒性肝炎"
        },
        {
            "value": "未分型病毒性肝炎",
            "label": "未分型病毒性肝炎"
        },
        {
            "value": "脊髓灰质炎",
            "label": "脊髓灰质炎"
        },
        {
            "value": "人感染高致病性禽流感",
            "label": "人感染高致病性禽流感"
        },
        {
            "value": "麻疹",
            "label": "麻疹"
        },
        {
            "value": "流行性出血热",
            "label": "流行性出血热"
        },
        {
            "value": "狂犬病",
            "label": "狂犬病"
        },
        {
            "value": "流行性乙型脑炎",
            "label": "流行性乙型脑炎"
        },
        {
            "value": "登革热",
            "label": "登革热"
        },
        {
            "value": "肺炭疽",
            "label": "肺炭疽"
        },
        {
            "value": "皮肤炭疽",
            "label": "皮肤炭疽"
        },
        {
            "value": "未分型炭疽",
            "label": "未分型炭疽"
        },
        {
            "value": "细菌性痢疾",
            "label": "细菌性痢疾"
        },
        {
            "value": "阿米巴性痢疾",
            "label": "阿米巴性痢疾"
        },
        {
            "value": "利福平耐药肺结核",
            "label": "利福平耐药肺结核"
        },
        {
            "value": "涂阳肺结核",
            "label": "涂阳肺结核"
        },
        {
            "value": "仅培阳肺结核",
            "label": "仅培阳肺结核"
        },
        {
            "value": "菌阴肺结核",
            "label": "菌阴肺结核"
        },
        {
            "value": "未痰检肺结核",
            "label": "未痰检肺结核"
        },
        {
            "value": "伤寒",
            "label": "伤寒"
        },
        {
            "value": "副伤寒",
            "label": "副伤寒"
        },
        {
            "value": "流行性脑脊髓膜炎",
            "label": "流行性脑脊髓膜炎"
        },
        {
            "value": "百日咳",
            "label": "百日咳"
        },
        {
            "value": "白喉",
            "label": "白喉"
        },
        {
            "value": "新生儿破伤风",
            "label": "新生儿破伤风"
        },
        {
            "value": "猩红热",
            "label": "猩红热"
        },
        {
            "value": "布鲁氏菌病",
            "label": "布鲁氏菌病"
        },
        {
            "value": "淋病",
            "label": "淋病"
        },
        {
            "value": "Ⅰ期梅毒",
            "label": "Ⅰ期梅毒"
        },
        {
            "value": "Ⅱ期梅毒",
            "label": "Ⅱ期梅毒"
        },
        {
            "value": "Ⅲ梅毒",
            "label": "Ⅲ梅毒"
        },
        {
            "value": "胎传梅毒",
            "label": "胎传梅毒"
        },
        {
            "value": "隐性梅毒",
            "label": "隐性梅毒"
        },
        {
            "value": "钩端螺旋体病",
            "label": "钩端螺旋体病"
        },
        {
            "value": "血吸虫病",
            "label": "血吸虫病"
        },
        {
            "value": "间日疟疾",
            "label": "间日疟疾"
        },
        {
            "value": "恶性疟疾",
            "label": "恶性疟疾"
        },
        {
            "value": "未分型疟疾",
            "label": "未分型疟疾"
        },
        {
            "value": "人感染H7N9禽流感",
            "label": "人感染H7N9禽流感"
        }
    ],
    "third": [
        {
            "value": "流行性感冒",
            "label": "流行性感冒"
        },
        {
            "value": "流行性腮腺炎",
            "label": "流行性腮腺炎"
        },
        {
            "value": "风疹",
            "label": "风疹"
        },
        {
            "value": "急性出血性结膜炎",
            "label": "急性出血性结膜炎"
        },
        {
            "value": "麻风病",
            "label": "麻风病"
        },
        {
            "value": "流行性和地方性斑疹伤寒",
            "label": "流行性和地方性斑疹伤寒"
        },
        {
            "value": "黑热病",
            "label": "黑热病"
        },
        {
            "value": "包虫病",
            "label": "包虫病"
        },
        {
            "value": "丝虫病",
            "label": "丝虫病"
        },
        {
            "value": "除霍乱、细菌性和阿米巴性痢疾、伤寒和副伤寒以外的感染性腹泻病",
            "label": "除霍乱、细菌性和阿米巴性痢疾、伤寒和副伤寒以外的感染性腹泻病"
        },
        {
            "value": "手足口病",
            "label": "手足口病"
        }
    ],
    "other": [
        {
            "value": "非淋菌性尿道炎",
            "label": "非淋菌性尿道炎"
        },
        {
            "value": "尖锐湿疣",
            "label": "尖锐湿疣"
        },
        {
            "value": "生殖器疱疹",
            "label": "生殖器疱疹"
        },
        {
            "value": "水痘",
            "label": "水痘"
        },
        {
            "value": "肝吸虫病",
            "label": "肝吸虫病"
        },
        {
            "value": "生殖道衣原体感染",
            "label": "生殖道衣原体感染"
        },
        {
            "value": "恙虫病",
            "label": "恙虫病"
        },
        {
            "value": "森林脑炎",
            "label": "森林脑炎"
        },
        {
            "value": "结核性胸膜炎",
            "label": "结核性胸膜炎"
        },
        {
            "value": "人感染猪链球菌",
            "label": "人感染猪链球菌"
        },
        {
            "value": "人粒细胞无形体病",
            "label": "人粒细胞无形体病"
        },
        {
            "value": "不明原因肺炎",
            "label": "不明原因肺炎"
        },
        {
            "value": "发热伴血小板减少综合征",
            "label": "发热伴血小板减少综合征"
        },
        {
            "value": "AFP",
            "label": "AFP"
        }
    ]
}